{
  "dir": "/Users/hongpengpeng/Projects/npm-security-detector/downloaded_packages/statsig-node-vercel/package",
  "fileCount": 5,
  "results": [
    {
      "file": "babel.config.js",
      "obfuscated": false
    },
    {
      "file": "dist/EdgeConfigDataAdapter.js",
      "obfuscated": false
    },
    {
      "file": "dist/index.js",
      "obfuscated": false
    },
    {
      "file": "jest.config.js",
      "obfuscated": false
    },
    {
      "file": "jest.setup.js",
      "obfuscated": false
    }
  ]
}